mewo_http_client/__init__.py
mewo_http_client/cli.py
mewo_http_client/lib.py
mewo_http_client/mub/__init__.py
mewo_http_client/mub/lib.py
mewo_http_client/mub/templates/__init__.py
mewo_http_client/mub/templates/lib.py
mewo_http_client-0.1.19.dist-info/METADATA
mewo_http_client-0.1.19.dist-info/WHEEL
mewo_http_client-0.1.19.dist-info/entry_points.txt
mewo_http_client-0.1.19.dist-info/RECORD
