Metadata-Version: 2.1
Name: mewo-http-client
Version: 0.1.19
Summary: 
Author: feluxe
Author-email: felix@meyerwolters.de
Requires-Python: >=3.9,<4.0
Classifier: Programming Language :: Python :: 3
Classifier: Programming Language :: Python :: 3.9
Classifier: Programming Language :: Python :: 3.10
Classifier: Programming Language :: Python :: 3.11
Classifier: Programming Language :: Python :: 3.12
Requires-Dist: requests (>=2,<3)
